REvoDesign/__init__.py
REvoDesign/hello_world.py
revodesign-0.0.0rc23.post1.dist-info/licenses/LICENSE
revodesign-0.0.0rc23.post1.dist-info/WHEEL
revodesign-0.0.0rc23.post1.dist-info/METADATA
revodesign-0.0.0rc23.post1.dist-info/RECORD
