Metadata-Version: 2.4
Name: REvoDesign
Version: 0.0.0rc23.post1
Summary: A PyMOL plugin that makes enzyme redesign tasks easier to all.
Author-email: Yinying Yao <yaoyy.hi@gmail.com>
Requires-Python: >=3.9
Classifier: Development Status :: 6 - Mature
Classifier: Operating System :: POSIX :: Linux
Classifier: Operating System :: MacOS :: MacOS X
Classifier: Intended Audience :: Developers
Classifier: License :: OSI Approved :: MIT License
Classifier: Programming Language :: Python :: 3 :: Only
Classifier: Programming Language :: Python :: 3.9
Classifier: Programming Language :: Python :: 3.10
Classifier: Programming Language :: Python :: 3.11
Classifier: Programming Language :: Python :: 3.12
License-File: LICENSE
Requires-Dist: typing-extensions>=4.9.0
Requires-Dist: immutabledict>=4.1.0
Requires-Dist: biopython>=1.81
Requires-Dist: joblib>=1.3.2
Requires-Dist: matplotlib>=3.6.0
Requires-Dist: pandas>=2.1.0
Requires-Dist: numpy<2.0.0
Requires-Dist: requests>=2.32.3
Requires-Dist: scikit-learn>=1.3.0
Requires-Dist: scipy>=1.11.2
Requires-Dist: pyOpenSSL>=23.3.0
Requires-Dist: pybiolib>=1.1.1666
Requires-Dist: hydra-core>=1.3.2
Requires-Dist: omegaconf>=2.3.0
Requires-Dist: rdkit>=2023.9.4
Requires-Dist: msgpack
Requires-Dist: RosettaPy>=0.2.11.post3
Requires-Dist: platformdirs
Requires-Dist: fastapi
Requires-Dist: uvicorn
Requires-Dist: requests
Requires-Dist: openpyxl
Requires-Dist: tqdm
Requires-Dist: webcolors
Project-URL: Documentation, https://github.com/YaoYinYing/REvoDesign/tree/main#readme
Project-URL: Source, https://github.com/YaoYinYing/REvoDesign
Project-URL: Tracker, https://github.com/YaoYinYing/REvoDesign/issues
